{"frames": {

"0.png":
{
	"frame": {"x":1,"y":1,"w":32,"h":32},
	"rotated": false,
	"trimmed": false,
	"spriteSourceSize": {"x":0,"y":0,"w":32,"h":32},
	"sourceSize": {"w":32,"h":32}
},
"1.png":
{
	"frame": {"x":35,"y":1,"w":32,"h":32},
	"rotated": false,
	"trimmed": false,
	"spriteSourceSize": {"x":0,"y":0,"w":32,"h":32},
	"sourceSize": {"w":32,"h":32}
},
"2.png":
{
	"frame": {"x":69,"y":1,"w":32,"h":32},
	"rotated": false,
	"trimmed": false,
	"spriteSourceSize": {"x":0,"y":0,"w":32,"h":32},
	"sourceSize": {"w":32,"h":32}
},
"3.png":
{
	"frame": {"x":1,"y":35,"w":32,"h":32},
	"rotated": false,
	"trimmed": false,
	"spriteSourceSize": {"x":0,"y":0,"w":32,"h":32},
	"sourceSize": {"w":32,"h":32}
},
"4.png":
{
	"frame": {"x":35,"y":35,"w":32,"h":32},
	"rotated": false,
	"trimmed": false,
	"spriteSourceSize": {"x":0,"y":0,"w":32,"h":32},
	"sourceSize": {"w":32,"h":32}
},
"5.png":
{
	"frame": {"x":69,"y":35,"w":32,"h":32},
	"rotated": false,
	"trimmed": false,
	"spriteSourceSize": {"x":0,"y":0,"w":32,"h":32},
	"sourceSize": {"w":32,"h":32}
},
"6.png":
{
	"frame": {"x":1,"y":69,"w":32,"h":32},
	"rotated": false,
	"trimmed": false,
	"spriteSourceSize": {"x":0,"y":0,"w":32,"h":32},
	"sourceSize": {"w":32,"h":32}
},
"7.png":
{
	"frame": {"x":35,"y":69,"w":32,"h":32},
	"rotated": false,
	"trimmed": false,
	"spriteSourceSize": {"x":0,"y":0,"w":32,"h":32},
	"sourceSize": {"w":32,"h":32}
}},
"animations": {
	"sprite": ["0.png","1.png","2.png","3.png","4.png","5.png","6.png","7.png"]
},
"meta": {
	"app": "https://www.codeandweb.com/texturepacker",
	"version": "1.0",
	"image": "chicken-spritesheet.png",
	"format": "RGBA8888",
	"size": {"w":102,"h":102},
	"scale": "1",
	"smartupdate": "$TexturePacker:SmartUpdate:018a7cfb72cf904476325d34dfade02c:a381fe6c251894fb5cf81b3a918d3320:a4c542335c859f191832e4150999d552$"
}
}
